misiss_mlops/__init__.py
misiss_mlops/config.py
misiss_mlops/dataset.py
misiss_mlops/entities/__init__.py
misiss_mlops/entities/data_params.py
misiss_mlops/entities/params.py
misiss_mlops/entities/train_params.py
misiss_mlops/modeling/__init__.py
misiss_mlops/modeling/predict.py
misiss_mlops/modeling/train.py
misiss_mlops-0.1.3.dist-info/WHEEL
misiss_mlops-0.1.3.dist-info/METADATA
misiss_mlops-0.1.3.dist-info/RECORD
