Metadata-Version: 2.3
Name: misiss_mlops
Version: 0.1.3
Summary: A short description of the project.
Author: Nikolai
Requires-Python: ~=3.10
Classifier: Programming Language :: Python :: 3
